{
    "DNDConfig": null,
    "_height_": {
        "type": "string",
        "value": "30dp"
    },
    "_left_": {
        "type": "string",
        "value": "27dp"
    },
    "_margin_": [
        0,
        0,
        0,
        0
    ],
    "_orientation_": 6,
    "_padding_": [
        0,
        0,
        0,
        0
    ],
    "_percent_": true,
    "_skin_": "sa19097eccc4416894935dd08585b110",
    "_top_": {
        "type": "string",
        "value": "25dp"
    },
    "_width_": {
        "type": "string",
        "value": "30dp"
    },
    "allboxes": [],
    "autogrowmode": 0,
    "canUpdateUI": true,
    "centerx": {
        "type": "string",
        "value": "50%"
    },
    "centery": {
        "type": "string",
        "value": "50%"
    },
    "children": [],
    "clipbounds": false,
    "containerweight": 100,
    "enablescrolling": true,
    "id": "flxInner",
    "info": null,
    "iscustomlayout": false,
    "isvisible": true,
    "kuid": "d9884438aab84c8a8d0a00164a59e6bc",
    "layouttype": 2,
    "name": "kony.ui.FlexContainer",
    "parent": "SquareListArea",
    "pf": "userwidgetmodel",
    "retaincontentalignment": false,
    "retainflexpositionproperties": false,
    "retainflowhorizontalalignment": false,
    "snapgridsize": 10,
    "snaptogrid": true,
    "wType": "FlexContainer",
    "widgetalignment": 1,
    "zindex": 1
}